used_by/__init__.py
used_by/main.py
used_by-0.1.4.dist-info/LICENSE
used_by-0.1.4.dist-info/METADATA
used_by-0.1.4.dist-info/WHEEL
used_by-0.1.4.dist-info/entry_points.txt
used_by-0.1.4.dist-info/top_level.txt
used_by-0.1.4.dist-info/RECORD
