Metadata-Version: 2.1
Name: used-by
Version: 0.1.4
Summary: Generate Used By badge from GitHub's dependencies information.
Author-email: shenxianpeng <xianpeng.shen@gmail.com>
License: MIT License
Project-URL: source, https://github.com/shenxianpeng/used-by
Project-URL: tracker, https://github.com/shenxianpeng/used-by/issues
Keywords: used by,dependencies
Classifier: Development Status :: 4 - Beta
Classifier: License :: OSI Approved :: MIT License
Classifier: Intended Audience :: Developers
Classifier: Natural Language :: English
Classifier: Operating System :: OS Independent
Classifier: Programming Language :: Python :: 3.8
Classifier: Programming Language :: Python :: 3.9
Classifier: Programming Language :: Python :: 3.10
Classifier: Programming Language :: Python :: 3.11
Classifier: Programming Language :: Python :: 3.12
Classifier: Topic :: Utilities
Classifier: Topic :: Software Development :: Build Tools
Classifier: Topic :: Software Development :: Libraries :: Python Modules
License-File: LICENSE
Requires-Dist: requests
Requires-Dist: bs4
